latex_tab_img_generation/__init__.py
latex_tab_img_generation/latex_gen.py
latex_tab_img_generation-0.1.dist-info/METADATA
latex_tab_img_generation-0.1.dist-info/WHEEL
latex_tab_img_generation-0.1.dist-info/top_level.txt
latex_tab_img_generation-0.1.dist-info/RECORD
